{
    "name": "Fancode Matches Data",
    "telegram": "https://t.me/livesportsplay",
    "owner": "Md Sohanur Rahman Hady",
    "last update time": "11:01:15 PM 29-03-2026",
    "matches": [
        {
            "event_category": "Racing",
            "title": "Real Zaragoza vs Racing Club",
            "src": "https://images.fancode.com/aig/match/v1774680543077/141492_CASACARDS_APP.png",
            "team_1": "Real Zaragoza",
            "team_2": "Racing Club",
            "status": "LIVE",
            "language": "ENGLISH",
            "event_name": "LALIGA Hypermotion 2025-26 Real Zaragoza",
            "match_name": "Real Zaragoza vs Racing Club | LALIGA Hypermotion 2025-26 Real Zaragoza [ENGLISH]",
            "match_id": "141492",
            "stream_url": "https://fancode-bd-srhady.vercel.app/real_zaragoza_vs_racing_club_141492_english.m3u8"
        },
        {
            "event_category": "Golf",
            "title": "Houston, vs Texas",
            "src": "https://images.fancode.com/skillup-uploads/cms-media/Texas-Children's-Houston-Open-2026-old-match-card.png",
            "team_1": "Houston,",
            "team_2": "Texas",
            "status": "LIVE",
            "language": "ENGLISH",
            "event_name": "Texas Children's Houston Open 2026 Main Feed - Day 4 Memorial Park Golf Course -",
            "match_name": "Houston, vs Texas | Texas Children's Houston Open 2026 Main Feed - Day 4 Memorial Park Golf Course - [ENGLISH]",
            "match_id": "141598",
            "stream_url": "https://fancode-bd-srhady.vercel.app/houston__vs_texas_141598_english.m3u8"
        },
        {
            "event_category": "Golf",
            "title": "Houston, vs Texas",
            "src": "https://images.fancode.com/skillup-uploads/cms-media/Texas-Children's-Houston-Open-2026-old-match-card.png",
            "team_1": "Houston,",
            "team_2": "Texas",
            "status": "LIVE",
            "language": "ENGLISH",
            "event_name": "Texas Children's Houston Open 2026 Featured Holes - Day 4 Memorial Park Golf Course -",
            "match_name": "Houston, vs Texas | Texas Children's Houston Open 2026 Featured Holes - Day 4 Memorial Park Golf Course - [ENGLISH]",
            "match_id": "141601",
            "stream_url": "https://fancode-bd-srhady.vercel.app/houston__vs_texas_141601_english.m3u8"
        },
        {
            "event_category": "Golf",
            "title": "Houston, vs Texas",
            "src": "https://images.fancode.com/skillup-uploads/cms-media/Texas-Children's-Houston-Open-2026-old-match-card.png",
            "team_1": "Houston,",
            "team_2": "Texas",
            "status": "LIVE",
            "language": "ENGLISH",
            "event_name": "Texas Children's Houston Open 2026 Featured Groups - Day 4 Memorial Park Golf Course -",
            "match_name": "Houston, vs Texas | Texas Children's Houston Open 2026 Featured Groups - Day 4 Memorial Park Golf Course - [ENGLISH]",
            "match_id": "141600",
            "stream_url": "https://fancode-bd-srhady.vercel.app/houston__vs_texas_141600_english.m3u8"
        },
        {
            "event_category": "Golf",
            "title": "Houston, vs Texas",
            "src": "https://images.fancode.com/skillup-uploads/cms-media/Texas-Children's-Houston-Open-2026-old-match-card.png",
            "team_1": "Houston,",
            "team_2": "Texas",
            "status": "LIVE",
            "language": "ENGLISH",
            "event_name": "Texas Children's Houston Open 2026 Marquee Group - Day 4 Memorial Park Golf Course -",
            "match_name": "Houston, vs Texas | Texas Children's Houston Open 2026 Marquee Group - Day 4 Memorial Park Golf Course - [ENGLISH]",
            "match_id": "141599",
            "stream_url": "https://fancode-bd-srhady.vercel.app/houston__vs_texas_141599_english.m3u8"
        },
        {
            "event_category": "Racing",
            "title": "The vs Americas",
            "src": "https://images.fancode.com/skillup-uploads/cms-media/Moto-GP-Unites-States_Web.jpg",
            "team_1": "The",
            "team_2": "Americas",
            "status": "LIVE",
            "language": "ENGLISH",
            "event_name": "RED BULL GRAND PRIX OF THE UNITED STATES 2026 Race Day Circuit Of",
            "match_name": "The vs Americas | RED BULL GRAND PRIX OF THE UNITED STATES 2026 Race Day Circuit Of [ENGLISH]",
            "match_id": "139932",
            "stream_url": "https://fancode-bd-srhady.vercel.app/the_vs_americas_139932_english.m3u8"
        }
    ]
}